environmentaltrends/__init__.py
environmentaltrends/data_prep.py
environmentaltrends/single_trend_analysis.py
environmentaltrends/trends.py
environmentaltrends/validation.py
environmentaltrends-0.0.4.dist-info/LICENSE
environmentaltrends-0.0.4.dist-info/METADATA
environmentaltrends-0.0.4.dist-info/WHEEL
environmentaltrends-0.0.4.dist-info/RECORD
